{"asset":{"version":"1.0","generatetool":"OSGBLab(www.osgblab.com)","gltfUpAxis":"Y"},"geometricError":105.91256,"root":{"boundingVolume":{"sphere":[-2938702.78746,4698964.92603,3146088.44953,71.93580]},"refine":"REPLACE","geometricError":64,"content":{"uri":"Tile_33.b3dm"},"children":[{"boundingVolume":{"sphere":[-2938702.78746,4698964.10183,3146088.44953,72.52134]},"geometricError":32,"content":{"uri":"Tile_33_L14_0.b3dm"},"children":[{"boundingVolume":{"sphere":[-2938702.78746,4698963.36171,3146088.44953,73.05108]},"geometricError":16,"content":{"uri":"Tile_33_L15_00.b3dm"},"children":[{"boundingVolume":{"sphere":[-2938702.76169,4698963.62322,3146088.29112,73.23089]},"geometricError":8,"content":{"uri":"Tile_33_L16_000.b3dm"},"children":[{"boundingVolume":{"sphere":[-2938702.77362,4698963.73925,3146088.39010,73.30298]},"geometricError":4,"content":{"uri":"Tile_33_L17_0000.b3dm"},"children":[{"boundingVolume":{"sphere":[-2938702.74382,4698963.69694,3146088.41316,73.42189]},"geometricError":2,"content":{"uri":"Tile_33_L18_00000t1.b3dm"},"children":[{"boundingVolume":{"sphere":[-2938702.77879,4698963.67763,3146088.40943,73.43187]},"geometricError":1,"content":{"uri":"Tile_33_L19_000000t3.b3dm"},"children":[{"boundingVolume":{"sphere":[-2938693.20368,4698976.60961,3146088.40715,57.81794]},"geometricError":0.50000,"content":{"uri":"Tile_33_L20_0000020t3.b3dm"},"children":[{"boundingVolume":{"sphere":[-2938674.74823,4698986.97964,3146088.38943,38.88545]},"geometricError":0.25000,"content":{"uri":"Tile_33_L21_00000220.b3dm"}},{"boundingVolume":{"sphere":[-2938710.70346,4698952.28523,3146089.30594,28.76982]},"geometricError":0.25000,"content":{"uri":"Tile_33_L21_00000230.b3dm"}}]},{"boundingVolume":{"sphere":[-2938740.86204,4698925.41399,3146095.96794,18.97823]},"geometricError":0.50000,"content":{"uri":"Tile_33_L20_0000030t3.b3dm"},"children":[{"boundingVolume":{"sphere":[-2938740.90293,4698925.39671,3146095.97394,18.94563]},"geometricError":0.25000,"content":{"uri":"Tile_33_L21_00000320.b3dm"},"children":[{"boundingVolume":{"sphere":[-2938740.91943,4698925.39072,3146095.97394,18.93166]},"geometricError":0.12500,"content":{"uri":"Tile_33_L22_000003200.b3dm"}}]}]}]}]}]}]}]}]}]}}
